tsc_utils/__init__.py
tsc_utils/codegen.py
tsc_utils/flags.py
tsc_utils/numbers.py
tsc_utils/py.typed
tsc_utils/util.py
tsc_utils/version.py
tsc_utils-0.2.5.dist-info/LICENSE.md
tsc_utils-0.2.5.dist-info/METADATA
tsc_utils-0.2.5.dist-info/WHEEL
tsc_utils-0.2.5.dist-info/top_level.txt
tsc_utils-0.2.5.dist-info/RECORD
